correlate/__init__.py
correlate/debug.py
correlate/experiments/scorefun.py
correlate-1.1.dist-info/LICENSE
correlate-1.1.dist-info/WHEEL
correlate-1.1.dist-info/METADATA
correlate-1.1.dist-info/RECORD
