Metadata-Version: 2.1
Name: correlate
Version: 1.1
Summary: Correlates two sets of data by matching
Home-page: https://github.com/larryhastings/correlate/
Author: Larry Hastings
Author-email: larry@hastings.org
Requires-Python: >=3.6
Classifier: Intended Audience :: Developers
Classifier: License :: OSI Approved :: BSD License
Classifier: Programming Language :: Python :: 3 :: Only
